dew_gwdata/__init__.py
dew_gwdata/aquarius_ts.py
dew_gwdata/aquarius_wp.py
dew_gwdata/charts.py
dew_gwdata/dwcr_form.pdf
dew_gwdata/extraction_data.py
dew_gwdata/gtslogs.py
dew_gwdata/gwdata.py
dew_gwdata/hydstra.py
dew_gwdata/las_to_alias.csv
dew_gwdata/logger20_dosbox.conf
dew_gwdata/logger20_dosbox.py
dew_gwdata/package_database.py
dew_gwdata/rainfall.py
dew_gwdata/sagd_api.py
dew_gwdata/sageodata_database.py
dew_gwdata/sageodata_datamart.py
dew_gwdata/spreadsheets.py
dew_gwdata/swims_metadata.py
dew_gwdata/utils.py
dew_gwdata/wde.py
dew_gwdata/wilma_reports.py
dew_gwdata/logger20_image/addpath.exe
dew_gwdata/logger20_image/autoexec.bat
dew_gwdata/logger20_image/config.sys
dew_gwdata/logger20_image/instal20.bat
dew_gwdata/logger20_image/l20.bat
dew_gwdata/logger20_image/l20comio.exe
dew_gwdata/logger20_image/readme.txt
dew_gwdata/logger20_image/BAT/A.BAT
dew_gwdata/logger20_image/BAT/BAT.BAT
dew_gwdata/logger20_image/BAT/BJT.BAT
dew_gwdata/logger20_image/BAT/C.BAT
dew_gwdata/logger20_image/BAT/CHT.BAT
dew_gwdata/logger20_image/BAT/COM.BAT
dew_gwdata/logger20_image/BAT/CONV.BAT
dew_gwdata/logger20_image/BAT/DAC.BAT
dew_gwdata/logger20_image/BAT/DBF.BAT
dew_gwdata/logger20_image/BAT/DR.BAT
dew_gwdata/logger20_image/BAT/GK.BAT
dew_gwdata/logger20_image/BAT/LAS.BAT
dew_gwdata/logger20_image/BAT/LOG.BAT
dew_gwdata/logger20_image/BAT/QA.BAT
dew_gwdata/logger20_image/BAT/QC.BAT
dew_gwdata/logger20_image/BAT/RJM.BAT
dew_gwdata/logger20_image/BAT/SD.BAT
dew_gwdata/logger20_image/BAT/SDU.BAT
dew_gwdata/logger20_image/BAT/UTILS.BAT
dew_gwdata/logger20_image/BAT/VF.BAT
dew_gwdata/logger20_image/BAT/W.BAT
dew_gwdata/logger20_image/LOGGER20/LOGGER.BAK
dew_gwdata/logger20_image/LOGGER20/LOGGER.INI
dew_gwdata/logger20_image/LOGGER20/LOGGER.PWD
dew_gwdata/logger20_image/LOGGER20/gridlist.ref
dew_gwdata/logger20_image/LOGGER20/logger.dme
dew_gwdata/logger20_image/LOGGER20/logger.fnt
dew_gwdata/logger20_image/LOGGER20/logger.id
dew_gwdata/logger20_image/LOGGER20/logger20.exe
dew_gwdata-0.113.1.dist-info/LICENSE
dew_gwdata-0.113.1.dist-info/METADATA
dew_gwdata-0.113.1.dist-info/WHEEL
dew_gwdata-0.113.1.dist-info/entry_points.txt
dew_gwdata-0.113.1.dist-info/top_level.txt
dew_gwdata-0.113.1.dist-info/RECORD
