Metadata-Version: 2.1
Name: dew_gwdata
Version: 0.113.1
Summary: Python module for accessing groundwater data internally at DEW
Home-page: http://github.com/dew-waterscience/dew_gwdata
Author: Kent Inverarity
Author-email: kent.inverarity@sa.gov.au
License-File: LICENSE
Requires-Dist: numpy
Requires-Dist: matplotlib
Requires-Dist: networkx
Requires-Dist: pillow
Requires-Dist: pandas
Requires-Dist: ipython
Requires-Dist: geopandas
Requires-Dist: rasterio
Requires-Dist: shapely
Requires-Dist: toml
Requires-Dist: requests
Requires-Dist: openpyxl
Requires-Dist: appdirs
Requires-Dist: lasio
Requires-Dist: python-sa-gwdata >=0.14
Requires-Dist: sageodata-db >=0.44
Requires-Dist: ausweather >=0.9
Requires-Dist: aquarius-webportal
Requires-Dist: click
Requires-Dist: pyodbc
Requires-Dist: sqlparse
Requires-Dist: sqlalchemy
Requires-Dist: fastapi
Requires-Dist: pydantic
Requires-Dist: pypdf
Requires-Dist: uvicorn
Requires-Dist: jinja2
Requires-Dist: pozo
